trend_app_protect/__init__.py
trend_app_protect/_version.py
trend_app_protect/agent.py
trend_app_protect/compat.py
trend_app_protect/config.py
trend_app_protect/context.py
trend_app_protect/counters.py
trend_app_protect/exceptions.py
trend_app_protect/import_monitor.py
trend_app_protect/logger.py
trend_app_protect/patcher.py
trend_app_protect/patcher_async.py
trend_app_protect/plugin_manager.py
trend_app_protect/singleton.py
trend_app_protect/start.py
trend_app_protect/util.py
trend_app_protect/wsgi.py
trend_app_protect/api/__init__.py
trend_app_protect/api/aws_lambda.py
trend_app_protect/api/azure_function.py
trend_app_protect/api/signals.py
trend_app_protect/deps/__init__.py
trend_app_protect/deps/functools_lru_cache.py
trend_app_protect/deps/libagent/__init__.py
trend_app_protect/deps/libagent/agent.h
trend_app_protect/deps/libagent/libagent-x86_64-Linux-gnu.so
trend_app_protect/deps/libagent/libagent-x86_64-Linux-musl.so
trend_app_protect/plugins/__init__.py
trend_app_protect/plugins/dbapi2_helper.py
trend_app_protect/plugins/plugin_django.py
trend_app_protect/plugins/plugin_fileio.py
trend_app_protect/plugins/plugin_flask.py
trend_app_protect/plugins/plugin_mysqldb.py
trend_app_protect/plugins/plugin_psycopg2.py
trend_app_protect/plugins/plugin_pymssql.py
trend_app_protect/plugins/plugin_pymysql.py
trend_app_protect/plugins/plugin_pyramid.py
trend_app_protect/plugins/plugin_pysqlite2.py
trend_app_protect/plugins/plugin_shell.py
trend_app_protect/plugins/plugin_sqlite3.py
trend_app_protect/plugins/plugin_tornado.py
trend_app_protect/plugins/plugin_tornado_async.py
trend_app_protect/plugins/plugin_werkzeug.py
trend_app_protect-4.6.2.dist-info/LICENSE
trend_app_protect-4.6.2.dist-info/METADATA
trend_app_protect-4.6.2.dist-info/WHEEL
trend_app_protect-4.6.2.dist-info/top_level.txt
trend_app_protect-4.6.2.dist-info/RECORD
