Metadata-Version: 2.1
Name: trend-app-protect
Version: 4.6.2
Summary: Trend Micro Cloud One Application Security
Home-page: https://www.trendmicro.com/en_us/business/products/hybrid-cloud/cloud-one-application-security.html
Author: Trend Micro
License: UNKNOWN
Platform: UNKNOWN
Classifier: Framework :: Django
Classifier: Framework :: Flask
Classifier: Framework :: Pyramid
Classifier: Intended Audience :: Developers
Classifier: License :: Other/Proprietary License
Classifier: Programming Language :: Python :: 3.5
Classifier: Programming Language :: Python :: 3.6
Classifier: Programming Language :: Python :: 3.7
Classifier: Programming Language :: Python :: 3.8
Classifier: Topic :: Security
License-File: LICENSE
Requires-Dist: cffi
